MANIFEST.in
README.rst
pyproject.toml
setup.cfg
setup.py
django_simple_async_jobs.egg-info/PKG-INFO
django_simple_async_jobs.egg-info/SOURCES.txt
django_simple_async_jobs.egg-info/dependency_links.txt
django_simple_async_jobs.egg-info/requires.txt
django_simple_async_jobs.egg-info/top_level.txt
simple_jobs/__init__.py
simple_jobs/admin.py
simple_jobs/apps.py
simple_jobs/constants.py
simple_jobs/models.py
simple_jobs/management/__init__.py
simple_jobs/management/commands/__init__.py
simple_jobs/management/commands/base_job_poller.py
simple_jobs/management/commands/one_off_job_poller.py
simple_jobs/management/commands/periodic_job_poller.py
simple_jobs/migrations/0001_initial.py
simple_jobs/migrations/0002_alter_job_status.py
simple_jobs/migrations/__init__.py