Metadata-Version: 2.1
Name: django-simple-async-jobs
Version: 0.1.7
Summary: A Django app for running periodic or one off jobs.
Home-page: https://github.com/OscarVegener/django-simple-async-jobs
Author: Bohdan Yaroshchuk
Author-email: oscar.vegener@gmail.com
Classifier: Environment :: Web Environment
Classifier: Framework :: Django
Classifier: Framework :: Django :: 4.1
Classifier: Intended Audience :: Developers
Classifier: License :: OSI Approved :: BSD License
Classifier: Operating System :: OS Independent
Classifier: Programming Language :: Python
Classifier: Programming Language :: Python :: 3
Classifier: Programming Language :: Python :: 3 :: Only
Classifier: Programming Language :: Python :: 3.11
Requires-Python: >=3.11
